{"regular": {"pts": {"all": {"0": 9, "1": 18, "2": 15, "3": 24, "4": 19, "5": 14, "6": 8, "7": 12, "8": 15, "9": 10, "10": 26, "11": 22, "12": 6, "13": 15, "14": 15, "15": 8, "16": 6, "17": 6, "18": 23, "19": 19, "20": 11, "21": 8, "22": 12}, "home": {"3": 24, "4": 19, "8": 15, "9": 10, "10": 26, "11": 22, "12": 6, "13": 15, "17": 6, "18": 23, "20": 11, "21": 8}, "away": {"0": 9, "1": 18, "2": 15, "5": 14, "6": 8, "7": 12, "14": 15, "15": 8, "16": 6, "19": 19, "22": 12}, "0 before": {"0": 9}, "3 after": {"0": 9, "11": 22, "21": 8}, "3 before": {"1": 18, "12": 6, "22": 12}, "2 after": {"1": 18, "3": 24, "4": 19, "5": 14, "7": 12, "8": 15, "9": 10, "12": 6, "13": 15, "14": 15, "15": 8, "16": 6, "17": 6, "19": 19, "20": 11}, "mon": {"1": 18, "5": 14, "9": 10, "16": 6, "20": 11}, "2 before": {"2": 15, "4": 19, "5": 14, "6": 8, "8": 15, "9": 10, "10": 26, "13": 15, "14": 15, "15": 8, "16": 6, "17": 6, "18": 23, "20": 11, "21": 8}, "1 after": {"2": 15, "6": 8, "10": 26, "18": 23}, "1 before": {"3": 24, "7": 12, "11": 22, "19": 19}, "nyk": {"21": 8}, "8 after": {"22": 12}}, "reb": {"all": {"0": 3, "1": 11, "2": 10, "3": 12, "4": 6, "5": 13, "6": 7, "7": 8, "8": 11, "9": 13, "10": 11, "11": 8, "12": 3, "13": 10, "14": 9, "15": 6, "16": 11, "17": 7, "18": 13, "19": 9, "20": 6, "21": 4, "22": 12}, "home": {"3": 12, "4": 6, "8": 11, "9": 13, "10": 11, "11": 8, "12": 3, "13": 10, "17": 7, "18": 13, "20": 6, "21": 4}, "away": {"0": 3, "1": 11, "2": 10, "5": 13, "6": 7, "7": 8, "14": 9, "15": 6, "16": 11, "19": 9, "22": 12}, "0 before": {"0": 3}, "3 after": {"0": 3, "11": 8, "21": 4}, "3 before": {"1": 11, "12": 3, "22": 12}, "2 after": {"1": 11, "3": 12, "4": 6, "5": 13, "7": 8, "8": 11, "9": 13, "12": 3, "13": 10, "14": 9, "15": 6, "16": 11, "17": 7, "19": 9, "20": 6}, "mon": {"1": 11, "5": 13, "9": 13, "16": 11, "20": 6}, "2 before": {"2": 10, "4": 6, "5": 13, "6": 7, "8": 11, "9": 13, "10": 11, "13": 10, "14": 9, "15": 6, "16": 11, "17": 7, "18": 13, "20": 6, "21": 4}, "1 after": {"2": 10, "6": 7, "10": 11, "18": 13}, "1 before": {"3": 12, "7": 8, "11": 8, "19": 9}, "nyk": {"21": 4}, "8 after": {"22": 12}}, "ast": {"all": {"0": 2, "1": 0, "2": 1, "3": 1, "4": 3, "5": 2, "6": 2, "7": 4, "8": 2, "9": 7, "10": 3, "11": 3, "12": 4, "13": 3, "14": 2, "15": 0, "16": 2, "17": 0, "18": 5, "19": 2, "20": 3, "21": 0, "22": 1}, "home": {"3": 1, "4": 3, "8": 2, "9": 7, "10": 3, "11": 3, "12": 4, "13": 3, "17": 0, "18": 5, "20": 3, "21": 0}, "away": {"0": 2, "1": 0, "2": 1, "5": 2, "6": 2, "7": 4, "14": 2, "15": 0, "16": 2, "19": 2, "22": 1}, "0 before": {"0": 2}, "3 after": {"0": 2, "11": 3, "21": 0}, "3 before": {"1": 0, "12": 4, "22": 1}, "2 after": {"1": 0, "3": 1, "4": 3, "5": 2, "7": 4, "8": 2, "9": 7, "12": 4, "13": 3, "14": 2, "15": 0, "16": 2, "17": 0, "19": 2, "20": 3}, "mon": {"1": 0, "5": 2, "9": 7, "16": 2, "20": 3}, "2 before": {"2": 1, "4": 3, "5": 2, "6": 2, "8": 2, "9": 7, "10": 3, "13": 3, "14": 2, "15": 0, "16": 2, "17": 0, "18": 5, "20": 3, "21": 0}, "1 after": {"2": 1, "6": 2, "10": 3, "18": 5}, "1 before": {"3": 1, "7": 4, "11": 3, "19": 2}, "nyk": {"21": 0}, "8 after": {"22": 1}}, "w score": {"all": {"0": 133, "1": 127, "2": 124, "3": 121, "4": 124, "5": 114, "6": 105, "7": 116, "8": 117, "9": 129, "10": 121, "11": 115, "12": 131, "13": 136, "14": 104, "15": 122, "16": 134, "17": 123, "18": 125, "19": 110, "20": 130, "21": 96, "22": 111}, "home": {"3": 121, "4": 124, "8": 117, "9": 129, "10": 121, "11": 115, "12": 131, "13": 136, "17": 123, "18": 125, "20": 130, "21": 96}, "away": {"0": 133, "1": 127, "2": 124, "5": 114, "6": 105, "7": 116, "14": 104, "15": 122, "16": 134, "19": 110, "22": 111}, "0 before": {"0": 133}, "3 after": {"0": 133, "11": 115, "21": 96}, "3 before": {"1": 127, "12": 131, "22": 111}, "2 after": {"1": 127, "3": 121, "4": 124, "5": 114, "7": 116, "8": 117, "9": 129, "12": 131, "13": 136, "14": 104, "15": 122, "16": 134, "17": 123, "19": 110, "20": 130}, "mon": {"1": 127, "5": 114, "9": 129, "16": 134, "20": 130}, "2 before": {"2": 124, "4": 124, "5": 114, "6": 105, "8": 117, "9": 129, "10": 121, "13": 136, "14": 104, "15": 122, "16": 134, "17": 123, "18": 125, "20": 130, "21": 96}, "1 after": {"2": 124, "6": 105, "10": 121, "18": 125}, "1 before": {"3": 121, "7": 116, "11": 115, "19": 110}, "nyk": {"21": 96}, "8 after": {"22": 111}}, "l score": {"all": {"0": 89, "1": 117, "2": 118, "3": 106, "4": 114, "5": 112, "6": 100, "7": 106, "8": 112, "9": 93, "10": 120, "11": 110, "12": 110, "13": 124, "14": 101, "15": 101, "16": 116, "17": 105, "18": 116, "19": 106, "20": 102, "21": 87, "22": 104}, "home": {"3": 106, "4": 114, "8": 112, "9": 93, "10": 120, "11": 110, "12": 110, "13": 124, "17": 105, "18": 116, "20": 102, "21": 87}, "away": {"0": 89, "1": 117, "2": 118, "5": 112, "6": 100, "7": 106, "14": 101, "15": 101, "16": 116, "19": 106, "22": 104}, "0 before": {"0": 89}, "3 after": {"0": 89, "11": 110, "21": 87}, "3 before": {"1": 117, "12": 110, "22": 104}, "2 after": {"1": 117, "3": 106, "4": 114, "5": 112, "7": 106, "8": 112, "9": 93, "12": 110, "13": 124, "14": 101, "15": 101, "16": 116, "17": 105, "19": 106, "20": 102}, "mon": {"1": 117, "5": 112, "9": 93, "16": 116, "20": 102}, "2 before": {"2": 118, "4": 114, "5": 112, "6": 100, "8": 112, "9": 93, "10": 120, "13": 124, "14": 101, "15": 101, "16": 116, "17": 105, "18": 116, "20": 102, "21": 87}, "1 after": {"2": 118, "6": 100, "10": 120, "18": 116}, "1 before": {"3": 106, "7": 106, "11": 110, "19": 106}, "nyk": {"21": 87}, "8 after": {"22": 104}}, "min": {"all": {"0": 23, "1": 29, "2": 36, "3": 31, "4": 32, "5": 30, "6": 26, "7": 28, "8": 28, "9": 21, "10": 30, "11": 34, "12": 22, "13": 21, "14": 29, "15": 22, "16": 24, "17": 21, "18": 33, "19": 21, "20": 23, "21": 21, "22": 29}, "home": {"3": 31, "4": 32, "8": 28, "9": 21, "10": 30, "11": 34, "12": 22, "13": 21, "17": 21, "18": 33, "20": 23, "21": 21}, "away": {"0": 23, "1": 29, "2": 36, "5": 30, "6": 26, "7": 28, "14": 29, "15": 22, "16": 24, "19": 21, "22": 29}, "0 before": {"0": 23}, "3 after": {"0": 23, "11": 34, "21": 21}, "3 before": {"1": 29, "12": 22, "22": 29}, "2 after": {"1": 29, "3": 31, "4": 32, "5": 30, "7": 28, "8": 28, "9": 21, "12": 22, "13": 21, "14": 29, "15": 22, "16": 24, "17": 21, "19": 21, "20": 23}, "mon": {"1": 29, "5": 30, "9": 21, "16": 24, "20": 23}, "2 before": {"2": 36, "4": 32, "5": 30, "6": 26, "8": 28, "9": 21, "10": 30, "13": 21, "14": 29, "15": 22, "16": 24, "17": 21, "18": 33, "20": 23, "21": 21}, "1 after": {"2": 36, "6": 26, "10": 30, "18": 33}, "1 before": {"3": 31, "7": 28, "11": 34, "19": 21}, "nyk": {"21": 21}, "8 after": {"22": 29}}, "fgm": {"all": {"0": 3, "1": 7, "2": 6, "3": 9, "4": 8, "5": 5, "6": 3, "7": 4, "8": 6, "9": 3, "10": 10, "11": 10, "12": 3, "13": 6, "14": 7, "15": 4, "16": 2, "17": 3, "18": 9, "19": 6, "20": 4, "21": 3, "22": 4}, "home": {"3": 9, "4": 8, "8": 6, "9": 3, "10": 10, "11": 10, "12": 3, "13": 6, "17": 3, "18": 9, "20": 4, "21": 3}, "away": {"0": 3, "1": 7, "2": 6, "5": 5, "6": 3, "7": 4, "14": 7, "15": 4, "16": 2, "19": 6, "22": 4}, "0 before": {"0": 3}, "3 after": {"0": 3, "11": 10, "21": 3}, "3 before": {"1": 7, "12": 3, "22": 4}, "2 after": {"1": 7, "3": 9, "4": 8, "5": 5, "7": 4, "8": 6, "9": 3, "12": 3, "13": 6, "14": 7, "15": 4, "16": 2, "17": 3, "19": 6, "20": 4}, "mon": {"1": 7, "5": 5, "9": 3, "16": 2, "20": 4}, "2 before": {"2": 6, "4": 8, "5": 5, "6": 3, "8": 6, "9": 3, "10": 10, "13": 6, "14": 7, "15": 4, "16": 2, "17": 3, "18": 9, "20": 4, "21": 3}, "1 after": {"2": 6, "6": 3, "10": 10, "18": 9}, "1 before": {"3": 9, "7": 4, "11": 10, "19": 6}, "nyk": {"21": 3}, "8 after": {"22": 4}}, "fga": {"all": {"0": 9, "1": 11, "2": 11, "3": 12, "4": 9, "5": 10, "6": 10, "7": 6, "8": 9, "9": 4, "10": 15, "11": 18, "12": 5, "13": 11, "14": 12, "15": 9, "16": 6, "17": 6, "18": 16, "19": 10, "20": 11, "21": 7, "22": 7}, "home": {"3": 12, "4": 9, "8": 9, "9": 4, "10": 15, "11": 18, "12": 5, "13": 11, "17": 6, "18": 16, "20": 11, "21": 7}, "away": {"0": 9, "1": 11, "2": 11, "5": 10, "6": 10, "7": 6, "14": 12, "15": 9, "16": 6, "19": 10, "22": 7}, "0 before": {"0": 9}, "3 after": {"0": 9, "11": 18, "21": 7}, "3 before": {"1": 11, "12": 5, "22": 7}, "2 after": {"1": 11, "3": 12, "4": 9, "5": 10, "7": 6, "8": 9, "9": 4, "12": 5, "13": 11, "14": 12, "15": 9, "16": 6, "17": 6, "19": 10, "20": 11}, "mon": {"1": 11, "5": 10, "9": 4, "16": 6, "20": 11}, "2 before": {"2": 11, "4": 9, "5": 10, "6": 10, "8": 9, "9": 4, "10": 15, "13": 11, "14": 12, "15": 9, "16": 6, "17": 6, "18": 16, "20": 11, "21": 7}, "1 after": {"2": 11, "6": 10, "10": 15, "18": 16}, "1 before": {"3": 12, "7": 6, "11": 18, "19": 10}, "nyk": {"21": 7}, "8 after": {"22": 7}}, "fg%": {"all": {"0": 33.3, "1": 63.6, "2": 54.5, "3": 75.0, "4": 88.9, "5": 50.0, "6": 30.0, "7": 66.7, "8": 66.7, "9": 75.0, "10": 66.7, "11": 55.6, "12": 60.0, "13": 54.5, "14": 58.3, "15": 44.4, "16": 33.3, "17": 50.0, "18": 56.3, "19": 60.0, "20": 36.4, "21": 42.9, "22": 57.1}, "home": {"3": 75.0, "4": 88.9, "8": 66.7, "9": 75.0, "10": 66.7, "11": 55.6, "12": 60.0, "13": 54.5, "17": 50.0, "18": 56.3, "20": 36.4, "21": 42.9}, "away": {"0": 33.3, "1": 63.6, "2": 54.5, "5": 50.0, "6": 30.0, "7": 66.7, "14": 58.3, "15": 44.4, "16": 33.3, "19": 60.0, "22": 57.1}, "0 before": {"0": 33.3}, "3 after": {"0": 33.3, "11": 55.6, "21": 42.9}, "3 before": {"1": 63.6, "12": 60.0, "22": 57.1}, "2 after": {"1": 63.6, "3": 75.0, "4": 88.9, "5": 50.0, "7": 66.7, "8": 66.7, "9": 75.0, "12": 60.0, "13": 54.5, "14": 58.3, "15": 44.4, "16": 33.3, "17": 50.0, "19": 60.0, "20": 36.4}, "mon": {"1": 63.6, "5": 50.0, "9": 75.0, "16": 33.3, "20": 36.4}, "2 before": {"2": 54.5, "4": 88.9, "5": 50.0, "6": 30.0, "8": 66.7, "9": 75.0, "10": 66.7, "13": 54.5, "14": 58.3, "15": 44.4, "16": 33.3, "17": 50.0, "18": 56.3, "20": 36.4, "21": 42.9}, "1 after": {"2": 54.5, "6": 30.0, "10": 66.7, "18": 56.3}, "1 before": {"3": 75.0, "7": 66.7, "11": 55.6, "19": 60.0}, "nyk": {"21": 42.9}, "8 after": {"22": 57.1}}, "3pm": {"all": {"0": 1, "1": 0, "2": 2, "3": 0, "4": 0, "5": 0, "6": 0, "7": 2, "8": 0, "9": 0, "10": 0, "11": 1, "12": 0, "13": 3, "14": 1, "15": 0, "16": 0, "17": 0, "18": 2, "19": 1, "20": 1, "21": 0, "22": 2}, "home": {"3": 0, "4": 0, "8": 0, "9": 0, "10": 0, "11": 1, "12": 0, "13": 3, "17": 0, "18": 2, "20": 1, "21": 0}, "away": {"0": 1, "1": 0, "2": 2, "5": 0, "6": 0, "7": 2, "14": 1, "15": 0, "16": 0, "19": 1, "22": 2}, "0 before": {"0": 1}, "3 after": {"0": 1, "11": 1, "21": 0}, "3 before": {"1": 0, "12": 0, "22": 2}, "2 after": {"1": 0, "3": 0, "4": 0, "5": 0, "7": 2, "8": 0, "9": 0, "12": 0, "13": 3, "14": 1, "15": 0, "16": 0, "17": 0, "19": 1, "20": 1}, "mon": {"1": 0, "5": 0, "9": 0, "16": 0, "20": 1}, "2 before": {"2": 2, "4": 0, "5": 0, "6": 0, "8": 0, "9": 0, "10": 0, "13": 3, "14": 1, "15": 0, "16": 0, "17": 0, "18": 2, "20": 1, "21": 0}, "1 after": {"2": 2, "6": 0, "10": 0, "18": 2}, "1 before": {"3": 0, "7": 2, "11": 1, "19": 1}, "nyk": {"21": 0}, "8 after": {"22": 2}}, "3pa": {"all": {"0": 4, "1": 0, "2": 4, "3": 1, "4": 1, "5": 1, "6": 2, "7": 2, "8": 0, "9": 0, "10": 1, "11": 3, "12": 2, "13": 5, "14": 1, "15": 2, "16": 1, "17": 0, "18": 3, "19": 1, "20": 5, "21": 1, "22": 4}, "home": {"3": 1, "4": 1, "8": 0, "9": 0, "10": 1, "11": 3, "12": 2, "13": 5, "17": 0, "18": 3, "20": 5, "21": 1}, "away": {"0": 4, "1": 0, "2": 4, "5": 1, "6": 2, "7": 2, "14": 1, "15": 2, "16": 1, "19": 1, "22": 4}, "0 before": {"0": 4}, "3 after": {"0": 4, "11": 3, "21": 1}, "3 before": {"1": 0, "12": 2, "22": 4}, "2 after": {"1": 0, "3": 1, "4": 1, "5": 1, "7": 2, "8": 0, "9": 0, "12": 2, "13": 5, "14": 1, "15": 2, "16": 1, "17": 0, "19": 1, "20": 5}, "mon": {"1": 0, "5": 1, "9": 0, "16": 1, "20": 5}, "2 before": {"2": 4, "4": 1, "5": 1, "6": 2, "8": 0, "9": 0, "10": 1, "13": 5, "14": 1, "15": 2, "16": 1, "17": 0, "18": 3, "20": 5, "21": 1}, "1 after": {"2": 4, "6": 2, "10": 1, "18": 3}, "1 before": {"3": 1, "7": 2, "11": 3, "19": 1}, "nyk": {"21": 1}, "8 after": {"22": 4}}, "3p%": {"all": {"0": 25.0, "1": 0.0, "2": 50.0, "3": 0.0, "4": 0.0, "5": 0.0, "6": 0.0, "7": 100.0, "8": 0.0, "9": 0.0, "10": 0.0, "11": 33.3, "12": 0.0, "13": 60.0, "14": 100.0, "15": 0.0, "16": 0.0, "17": 0.0, "18": 66.7, "19": 100.0, "20": 20.0, "21": 0.0, "22": 50.0}, "home": {"3": 0.0, "4": 0.0, "8": 0.0, "9": 0.0, "10": 0.0, "11": 33.3, "12": 0.0, "13": 60.0, "17": 0.0, "18": 66.7, "20": 20.0, "21": 0.0}, "away": {"0": 25.0, "1": 0.0, "2": 50.0, "5": 0.0, "6": 0.0, "7": 100.0, "14": 100.0, "15": 0.0, "16": 0.0, "19": 100.0, "22": 50.0}, "0 before": {"0": 25.0}, "3 after": {"0": 25.0, "11": 33.3, "21": 0.0}, "3 before": {"1": 0.0, "12": 0.0, "22": 50.0}, "2 after": {"1": 0.0, "3": 0.0, "4": 0.0, "5": 0.0, "7": 100.0, "8": 0.0, "9": 0.0, "12": 0.0, "13": 60.0, "14": 100.0, "15": 0.0, "16": 0.0, "17": 0.0, "19": 100.0, "20": 20.0}, "mon": {"1": 0.0, "5": 0.0, "9": 0.0, "16": 0.0, "20": 20.0}, "2 before": {"2": 50.0, "4": 0.0, "5": 0.0, "6": 0.0, "8": 0.0, "9": 0.0, "10": 0.0, "13": 60.0, "14": 100.0, "15": 0.0, "16": 0.0, "17": 0.0, "18": 66.7, "20": 20.0, "21": 0.0}, "1 after": {"2": 50.0, "6": 0.0, "10": 0.0, "18": 66.7}, "1 before": {"3": 0.0, "7": 100.0, "11": 33.3, "19": 100.0}, "nyk": {"21": 0.0}, "8 after": {"22": 50.0}}, "ftm": {"all": {"0": 2, "1": 4, "2": 1, "3": 6, "4": 3, "5": 4, "6": 2, "7": 2, "8": 3, "9": 4, "10": 6, "11": 1, "12": 0, "13": 0, "14": 0, "15": 0, "16": 2, "17": 0, "18": 3, "19": 6, "20": 2, "21": 2, "22": 2}, "home": {"3": 6, "4": 3, "8": 3, "9": 4, "10": 6, "11": 1, "12": 0, "13": 0, "17": 0, "18": 3, "20": 2, "21": 2}, "away": {"0": 2, "1": 4, "2": 1, "5": 4, "6": 2, "7": 2, "14": 0, "15": 0, "16": 2, "19": 6, "22": 2}, "0 before": {"0": 2}, "3 after": {"0": 2, "11": 1, "21": 2}, "3 before": {"1": 4, "12": 0, "22": 2}, "2 after": {"1": 4, "3": 6, "4": 3, "5": 4, "7": 2, "8": 3, "9": 4, "12": 0, "13": 0, "14": 0, "15": 0, "16": 2, "17": 0, "19": 6, "20": 2}, "mon": {"1": 4, "5": 4, "9": 4, "16": 2, "20": 2}, "2 before": {"2": 1, "4": 3, "5": 4, "6": 2, "8": 3, "9": 4, "10": 6, "13": 0, "14": 0, "15": 0, "16": 2, "17": 0, "18": 3, "20": 2, "21": 2}, "1 after": {"2": 1, "6": 2, "10": 6, "18": 3}, "1 before": {"3": 6, "7": 2, "11": 1, "19": 6}, "nyk": {"21": 2}, "8 after": {"22": 2}}, "fta": {"all": {"0": 2, "1": 4, "2": 2, "3": 7, "4": 3, "5": 6, "6": 4, "7": 2, "8": 4, "9": 4, "10": 6, "11": 3, "12": 0, "13": 0, "14": 1, "15": 0, "16": 2, "17": 0, "18": 4, "19": 7, "20": 2, "21": 2, "22": 2}, "home": {"3": 7, "4": 3, "8": 4, "9": 4, "10": 6, "11": 3, "12": 0, "13": 0, "17": 0, "18": 4, "20": 2, "21": 2}, "away": {"0": 2, "1": 4, "2": 2, "5": 6, "6": 4, "7": 2, "14": 1, "15": 0, "16": 2, "19": 7, "22": 2}, "0 before": {"0": 2}, "3 after": {"0": 2, "11": 3, "21": 2}, "3 before": {"1": 4, "12": 0, "22": 2}, "2 after": {"1": 4, "3": 7, "4": 3, "5": 6, "7": 2, "8": 4, "9": 4, "12": 0, "13": 0, "14": 1, "15": 0, "16": 2, "17": 0, "19": 7, "20": 2}, "mon": {"1": 4, "5": 6, "9": 4, "16": 2, "20": 2}, "2 before": {"2": 2, "4": 3, "5": 6, "6": 4, "8": 4, "9": 4, "10": 6, "13": 0, "14": 1, "15": 0, "16": 2, "17": 0, "18": 4, "20": 2, "21": 2}, "1 after": {"2": 2, "6": 4, "10": 6, "18": 4}, "1 before": {"3": 7, "7": 2, "11": 3, "19": 7}, "nyk": {"21": 2}, "8 after": {"22": 2}}, "ft%": {"all": {"0": 100.0, "1": 100.0, "2": 50.0, "3": 85.7, "4": 100.0, "5": 66.7, "6": 50.0, "7": 100.0, "8": 75.0, "9": 100.0, "10": 100.0, "11": 33.3, "12": 0.0, "13": 0.0, "14": 0.0, "15": 0.0, "16": 100.0, "17": 0.0, "18": 75.0, "19": 85.7, "20": 100.0, "21": 100.0, "22": 100.0}, "home": {"3": 85.7, "4": 100.0, "8": 75.0, "9": 100.0, "10": 100.0, "11": 33.3, "12": 0.0, "13": 0.0, "17": 0.0, "18": 75.0, "20": 100.0, "21": 100.0}, "away": {"0": 100.0, "1": 100.0, "2": 50.0, "5": 66.7, "6": 50.0, "7": 100.0, "14": 0.0, "15": 0.0, "16": 100.0, "19": 85.7, "22": 100.0}, "0 before": {"0": 100.0}, "3 after": {"0": 100.0, "11": 33.3, "21": 100.0}, "3 before": {"1": 100.0, "12": 0.0, "22": 100.0}, "2 after": {"1": 100.0, "3": 85.7, "4": 100.0, "5": 66.7, "7": 100.0, "8": 75.0, "9": 100.0, "12": 0.0, "13": 0.0, "14": 0.0, "15": 0.0, "16": 100.0, "17": 0.0, "19": 85.7, "20": 100.0}, "mon": {"1": 100.0, "5": 66.7, "9": 100.0, "16": 100.0, "20": 100.0}, "2 before": {"2": 50.0, "4": 100.0, "5": 66.7, "6": 50.0, "8": 75.0, "9": 100.0, "10": 100.0, "13": 0.0, "14": 0.0, "15": 0.0, "16": 100.0, "17": 0.0, "18": 75.0, "20": 100.0, "21": 100.0}, "1 after": {"2": 50.0, "6": 50.0, "10": 100.0, "18": 75.0}, "1 before": {"3": 85.7, "7": 100.0, "11": 33.3, "19": 85.7}, "nyk": {"21": 100.0}, "8 after": {"22": 100.0}}, "blk": {"all": {"0": 3, "1": 0, "2": 0, "3": 2, "4": 0, "5": 1, "6": 0, "7": 0, "8": 0, "9": 3, "10": 3, "11": 1, "12": 2, "13": 2, "14": 4, "15": 0, "16": 1, "17": 1, "18": 3, "19": 1, "20": 2, "21": 0, "22": 1}, "home": {"3": 2, "4": 0, "8": 0, "9": 3, "10": 3, "11": 1, "12": 2, "13": 2, "17": 1, "18": 3, "20": 2, "21": 0}, "away": {"0": 3, "1": 0, "2": 0, "5": 1, "6": 0, "7": 0, "14": 4, "15": 0, "16": 1, "19": 1, "22": 1}, "0 before": {"0": 3}, "3 after": {"0": 3, "11": 1, "21": 0}, "3 before": {"1": 0, "12": 2, "22": 1}, "2 after": {"1": 0, "3": 2, "4": 0, "5": 1, "7": 0, "8": 0, "9": 3, "12": 2, "13": 2, "14": 4, "15": 0, "16": 1, "17": 1, "19": 1, "20": 2}, "mon": {"1": 0, "5": 1, "9": 3, "16": 1, "20": 2}, "2 before": {"2": 0, "4": 0, "5": 1, "6": 0, "8": 0, "9": 3, "10": 3, "13": 2, "14": 4, "15": 0, "16": 1, "17": 1, "18": 3, "20": 2, "21": 0}, "1 after": {"2": 0, "6": 0, "10": 3, "18": 3}, "1 before": {"3": 2, "7": 0, "11": 1, "19": 1}, "nyk": {"21": 0}, "8 after": {"22": 1}}, "stl": {"all": {"0": 1, "1": 0, "2": 0, "3": 1, "4": 0, "5": 0, "6": 1, "7": 1, "8": 0, "9": 1, "10": 1, "11": 0, "12": 1, "13": 0, "14": 0, "15": 0, "16": 0, "17": 1, "18": 0, "19": 1, "20": 0, "21": 1, "22": 0}, "home": {"3": 1, "4": 0, "8": 0, "9": 1, "10": 1, "11": 0, "12": 1, "13": 0, "17": 1, "18": 0, "20": 0, "21": 1}, "away": {"0": 1, "1": 0, "2": 0, "5": 0, "6": 1, "7": 1, "14": 0, "15": 0, "16": 0, "19": 1, "22": 0}, "0 before": {"0": 1}, "3 after": {"0": 1, "11": 0, "21": 1}, "3 before": {"1": 0, "12": 1, "22": 0}, "2 after": {"1": 0, "3": 1, "4": 0, "5": 0, "7": 1, "8": 0, "9": 1, "12": 1, "13": 0, "14": 0, "15": 0, "16": 0, "17": 1, "19": 1, "20": 0}, "mon": {"1": 0, "5": 0, "9": 1, "16": 0, "20": 0}, "2 before": {"2": 0, "4": 0, "5": 0, "6": 1, "8": 0, "9": 1, "10": 1, "13": 0, "14": 0, "15": 0, "16": 0, "17": 1, "18": 0, "20": 0, "21": 1}, "1 after": {"2": 0, "6": 1, "10": 1, "18": 0}, "1 before": {"3": 1, "7": 1, "11": 0, "19": 1}, "nyk": {"21": 1}, "8 after": {"22": 0}}, "pf": {"all": {"0": 2, "1": 6, "2": 3, "3": 3, "4": 5, "5": 3, "6": 2, "7": 4, "8": 5, "9": 3, "10": 5, "11": 4, "12": 1, "13": 0, "14": 6, "15": 1, "16": 6, "17": 1, "18": 5, "19": 2, "20": 1, "21": 4, "22": 1}, "home": {"3": 3, "4": 5, "8": 5, "9": 3, "10": 5, "11": 4, "12": 1, "13": 0, "17": 1, "18": 5, "20": 1, "21": 4}, "away": {"0": 2, "1": 6, "2": 3, "5": 3, "6": 2, "7": 4, "14": 6, "15": 1, "16": 6, "19": 2, "22": 1}, "0 before": {"0": 2}, "3 after": {"0": 2, "11": 4, "21": 4}, "3 before": {"1": 6, "12": 1, "22": 1}, "2 after": {"1": 6, "3": 3, "4": 5, "5": 3, "7": 4, "8": 5, "9": 3, "12": 1, "13": 0, "14": 6, "15": 1, "16": 6, "17": 1, "19": 2, "20": 1}, "mon": {"1": 6, "5": 3, "9": 3, "16": 6, "20": 1}, "2 before": {"2": 3, "4": 5, "5": 3, "6": 2, "8": 5, "9": 3, "10": 5, "13": 0, "14": 6, "15": 1, "16": 6, "17": 1, "18": 5, "20": 1, "21": 4}, "1 after": {"2": 3, "6": 2, "10": 5, "18": 5}, "1 before": {"3": 3, "7": 4, "11": 4, "19": 2}, "nyk": {"21": 4}, "8 after": {"22": 1}}, "to": {"all": {"0": 1, "1": 1, "2": 0, "3": 1, "4": 2, "5": 0, "6": 1, "7": 1, "8": 1, "9": 0, "10": 3, "11": 0, "12": 0, "13": 0, "14": 2, "15": 0, "16": 2, "17": 3, "18": 2, "19": 0, "20": 0, "21": 4, "22": 3}, "home": {"3": 1, "4": 2, "8": 1, "9": 0, "10": 3, "11": 0, "12": 0, "13": 0, "17": 3, "18": 2, "20": 0, "21": 4}, "away": {"0": 1, "1": 1, "2": 0, "5": 0, "6": 1, "7": 1, "14": 2, "15": 0, "16": 2, "19": 0, "22": 3}, "0 before": {"0": 1}, "3 after": {"0": 1, "11": 0, "21": 4}, "3 before": {"1": 1, "12": 0, "22": 3}, "2 after": {"1": 1, "3": 1, "4": 2, "5": 0, "7": 1, "8": 1, "9": 0, "12": 0, "13": 0, "14": 2, "15": 0, "16": 2, "17": 3, "19": 0, "20": 0}, "mon": {"1": 1, "5": 0, "9": 0, "16": 2, "20": 0}, "2 before": {"2": 0, "4": 2, "5": 0, "6": 1, "8": 1, "9": 0, "10": 3, "13": 0, "14": 2, "15": 0, "16": 2, "17": 3, "18": 2, "20": 0, "21": 4}, "1 after": {"2": 0, "6": 1, "10": 3, "18": 2}, "1 before": {"3": 1, "7": 1, "11": 0, "19": 0}, "nyk": {"21": 4}, "8 after": {"22": 3}}}, "postseason": {"pts": {"all": {}, "home": {}, "away": {}}, "reb": {"all": {}, "home": {}, "away": {}}, "ast": {"all": {}, "home": {}, "away": {}}, "w score": {"all": {}, "home": {}, "away": {}}, "l score": {"all": {}, "home": {}, "away": {}}, "min": {"all": {}, "home": {}, "away": {}}, "fgm": {"all": {}, "home": {}, "away": {}}, "fga": {"all": {}, "home": {}, "away": {}}, "fg%": {"all": {}, "home": {}, "away": {}}, "3pm": {"all": {}, "home": {}, "away": {}}, "3pa": {"all": {}, "home": {}, "away": {}}, "3p%": {"all": {}, "home": {}, "away": {}}, "ftm": {"all": {}, "home": {}, "away": {}}, "fta": {"all": {}, "home": {}, "away": {}}, "ft%": {"all": {}, "home": {}, "away": {}}, "blk": {"all": {}, "home": {}, "away": {}}, "stl": {"all": {}, "home": {}, "away": {}}, "pf": {"all": {}, "home": {}, "away": {}}, "to": {"all": {}, "home": {}, "away": {}}}, "full": {"pts": {"all": {"0": 9, "1": 18, "2": 15, "3": 24, "4": 19, "5": 14, "6": 8, "7": 12, "8": 15, "9": 10, "10": 26, "11": 22, "12": 6, "13": 15, "14": 15, "15": 8, "16": 6, "17": 6, "18": 23, "19": 19, "20": 11, "21": 8, "22": 12}, "home": {"3": 24, "4": 19, "8": 15, "9": 10, "10": 26, "11": 22, "12": 6, "13": 15, "17": 6, "18": 23, "20": 11, "21": 8}, "away": {"0": 9, "1": 18, "2": 15, "5": 14, "6": 8, "7": 12, "14": 15, "15": 8, "16": 6, "19": 19, "22": 12}, "0 before": {"0": 9}, "3 after": {"0": 9, "11": 22, "21": 8}, "3 before": {"1": 18, "12": 6, "22": 12}, "2 after": {"1": 18, "3": 24, "4": 19, "5": 14, "7": 12, "8": 15, "9": 10, "12": 6, "13": 15, "14": 15, "15": 8, "16": 6, "17": 6, "19": 19, "20": 11}, "mon": {"1": 18, "5": 14, "9": 10, "16": 6, "20": 11}, "2 before": {"2": 15, "4": 19, "5": 14, "6": 8, "8": 15, "9": 10, "10": 26, "13": 15, "14": 15, "15": 8, "16": 6, "17": 6, "18": 23, "20": 11, "21": 8}, "1 after": {"2": 15, "6": 8, "10": 26, "18": 23}, "1 before": {"3": 24, "7": 12, "11": 22, "19": 19}, "nyk": {"21": 8}, "8 after": {"22": 12}}, "reb": {"all": {"0": 3, "1": 11, "2": 10, "3": 12, "4": 6, "5": 13, "6": 7, "7": 8, "8": 11, "9": 13, "10": 11, "11": 8, "12": 3, "13": 10, "14": 9, "15": 6, "16": 11, "17": 7, "18": 13, "19": 9, "20": 6, "21": 4, "22": 12}, "home": {"3": 12, "4": 6, "8": 11, "9": 13, "10": 11, "11": 8, "12": 3, "13": 10, "17": 7, "18": 13, "20": 6, "21": 4}, "away": {"0": 3, "1": 11, "2": 10, "5": 13, "6": 7, "7": 8, "14": 9, "15": 6, "16": 11, "19": 9, "22": 12}, "0 before": {"0": 3}, "3 after": {"0": 3, "11": 8, "21": 4}, "3 before": {"1": 11, "12": 3, "22": 12}, "2 after": {"1": 11, "3": 12, "4": 6, "5": 13, "7": 8, "8": 11, "9": 13, "12": 3, "13": 10, "14": 9, "15": 6, "16": 11, "17": 7, "19": 9, "20": 6}, "mon": {"1": 11, "5": 13, "9": 13, "16": 11, "20": 6}, "2 before": {"2": 10, "4": 6, "5": 13, "6": 7, "8": 11, "9": 13, "10": 11, "13": 10, "14": 9, "15": 6, "16": 11, "17": 7, "18": 13, "20": 6, "21": 4}, "1 after": {"2": 10, "6": 7, "10": 11, "18": 13}, "1 before": {"3": 12, "7": 8, "11": 8, "19": 9}, "nyk": {"21": 4}, "8 after": {"22": 12}}, "ast": {"all": {"0": 2, "1": 0, "2": 1, "3": 1, "4": 3, "5": 2, "6": 2, "7": 4, "8": 2, "9": 7, "10": 3, "11": 3, "12": 4, "13": 3, "14": 2, "15": 0, "16": 2, "17": 0, "18": 5, "19": 2, "20": 3, "21": 0, "22": 1}, "home": {"3": 1, "4": 3, "8": 2, "9": 7, "10": 3, "11": 3, "12": 4, "13": 3, "17": 0, "18": 5, "20": 3, "21": 0}, "away": {"0": 2, "1": 0, "2": 1, "5": 2, "6": 2, "7": 4, "14": 2, "15": 0, "16": 2, "19": 2, "22": 1}, "0 before": {"0": 2}, "3 after": {"0": 2, "11": 3, "21": 0}, "3 before": {"1": 0, "12": 4, "22": 1}, "2 after": {"1": 0, "3": 1, "4": 3, "5": 2, "7": 4, "8": 2, "9": 7, "12": 4, "13": 3, "14": 2, "15": 0, "16": 2, "17": 0, "19": 2, "20": 3}, "mon": {"1": 0, "5": 2, "9": 7, "16": 2, "20": 3}, "2 before": {"2": 1, "4": 3, "5": 2, "6": 2, "8": 2, "9": 7, "10": 3, "13": 3, "14": 2, "15": 0, "16": 2, "17": 0, "18": 5, "20": 3, "21": 0}, "1 after": {"2": 1, "6": 2, "10": 3, "18": 5}, "1 before": {"3": 1, "7": 4, "11": 3, "19": 2}, "nyk": {"21": 0}, "8 after": {"22": 1}}, "w score": {"all": {"0": 133, "1": 127, "2": 124, "3": 121, "4": 124, "5": 114, "6": 105, "7": 116, "8": 117, "9": 129, "10": 121, "11": 115, "12": 131, "13": 136, "14": 104, "15": 122, "16": 134, "17": 123, "18": 125, "19": 110, "20": 130, "21": 96, "22": 111}, "home": {"3": 121, "4": 124, "8": 117, "9": 129, "10": 121, "11": 115, "12": 131, "13": 136, "17": 123, "18": 125, "20": 130, "21": 96}, "away": {"0": 133, "1": 127, "2": 124, "5": 114, "6": 105, "7": 116, "14": 104, "15": 122, "16": 134, "19": 110, "22": 111}, "0 before": {"0": 133}, "3 after": {"0": 133, "11": 115, "21": 96}, "3 before": {"1": 127, "12": 131, "22": 111}, "2 after": {"1": 127, "3": 121, "4": 124, "5": 114, "7": 116, "8": 117, "9": 129, "12": 131, "13": 136, "14": 104, "15": 122, "16": 134, "17": 123, "19": 110, "20": 130}, "mon": {"1": 127, "5": 114, "9": 129, "16": 134, "20": 130}, "2 before": {"2": 124, "4": 124, "5": 114, "6": 105, "8": 117, "9": 129, "10": 121, "13": 136, "14": 104, "15": 122, "16": 134, "17": 123, "18": 125, "20": 130, "21": 96}, "1 after": {"2": 124, "6": 105, "10": 121, "18": 125}, "1 before": {"3": 121, "7": 116, "11": 115, "19": 110}, "nyk": {"21": 96}, "8 after": {"22": 111}}, "l score": {"all": {"0": 89, "1": 117, "2": 118, "3": 106, "4": 114, "5": 112, "6": 100, "7": 106, "8": 112, "9": 93, "10": 120, "11": 110, "12": 110, "13": 124, "14": 101, "15": 101, "16": 116, "17": 105, "18": 116, "19": 106, "20": 102, "21": 87, "22": 104}, "home": {"3": 106, "4": 114, "8": 112, "9": 93, "10": 120, "11": 110, "12": 110, "13": 124, "17": 105, "18": 116, "20": 102, "21": 87}, "away": {"0": 89, "1": 117, "2": 118, "5": 112, "6": 100, "7": 106, "14": 101, "15": 101, "16": 116, "19": 106, "22": 104}, "0 before": {"0": 89}, "3 after": {"0": 89, "11": 110, "21": 87}, "3 before": {"1": 117, "12": 110, "22": 104}, "2 after": {"1": 117, "3": 106, "4": 114, "5": 112, "7": 106, "8": 112, "9": 93, "12": 110, "13": 124, "14": 101, "15": 101, "16": 116, "17": 105, "19": 106, "20": 102}, "mon": {"1": 117, "5": 112, "9": 93, "16": 116, "20": 102}, "2 before": {"2": 118, "4": 114, "5": 112, "6": 100, "8": 112, "9": 93, "10": 120, "13": 124, "14": 101, "15": 101, "16": 116, "17": 105, "18": 116, "20": 102, "21": 87}, "1 after": {"2": 118, "6": 100, "10": 120, "18": 116}, "1 before": {"3": 106, "7": 106, "11": 110, "19": 106}, "nyk": {"21": 87}, "8 after": {"22": 104}}, "min": {"all": {"0": 23, "1": 29, "2": 36, "3": 31, "4": 32, "5": 30, "6": 26, "7": 28, "8": 28, "9": 21, "10": 30, "11": 34, "12": 22, "13": 21, "14": 29, "15": 22, "16": 24, "17": 21, "18": 33, "19": 21, "20": 23, "21": 21, "22": 29}, "home": {"3": 31, "4": 32, "8": 28, "9": 21, "10": 30, "11": 34, "12": 22, "13": 21, "17": 21, "18": 33, "20": 23, "21": 21}, "away": {"0": 23, "1": 29, "2": 36, "5": 30, "6": 26, "7": 28, "14": 29, "15": 22, "16": 24, "19": 21, "22": 29}, "0 before": {"0": 23}, "3 after": {"0": 23, "11": 34, "21": 21}, "3 before": {"1": 29, "12": 22, "22": 29}, "2 after": {"1": 29, "3": 31, "4": 32, "5": 30, "7": 28, "8": 28, "9": 21, "12": 22, "13": 21, "14": 29, "15": 22, "16": 24, "17": 21, "19": 21, "20": 23}, "mon": {"1": 29, "5": 30, "9": 21, "16": 24, "20": 23}, "2 before": {"2": 36, "4": 32, "5": 30, "6": 26, "8": 28, "9": 21, "10": 30, "13": 21, "14": 29, "15": 22, "16": 24, "17": 21, "18": 33, "20": 23, "21": 21}, "1 after": {"2": 36, "6": 26, "10": 30, "18": 33}, "1 before": {"3": 31, "7": 28, "11": 34, "19": 21}, "nyk": {"21": 21}, "8 after": {"22": 29}}, "fgm": {"all": {"0": 3, "1": 7, "2": 6, "3": 9, "4": 8, "5": 5, "6": 3, "7": 4, "8": 6, "9": 3, "10": 10, "11": 10, "12": 3, "13": 6, "14": 7, "15": 4, "16": 2, "17": 3, "18": 9, "19": 6, "20": 4, "21": 3, "22": 4}, "home": {"3": 9, "4": 8, "8": 6, "9": 3, "10": 10, "11": 10, "12": 3, "13": 6, "17": 3, "18": 9, "20": 4, "21": 3}, "away": {"0": 3, "1": 7, "2": 6, "5": 5, "6": 3, "7": 4, "14": 7, "15": 4, "16": 2, "19": 6, "22": 4}, "0 before": {"0": 3}, "3 after": {"0": 3, "11": 10, "21": 3}, "3 before": {"1": 7, "12": 3, "22": 4}, "2 after": {"1": 7, "3": 9, "4": 8, "5": 5, "7": 4, "8": 6, "9": 3, "12": 3, "13": 6, "14": 7, "15": 4, "16": 2, "17": 3, "19": 6, "20": 4}, "mon": {"1": 7, "5": 5, "9": 3, "16": 2, "20": 4}, "2 before": {"2": 6, "4": 8, "5": 5, "6": 3, "8": 6, "9": 3, "10": 10, "13": 6, "14": 7, "15": 4, "16": 2, "17": 3, "18": 9, "20": 4, "21": 3}, "1 after": {"2": 6, "6": 3, "10": 10, "18": 9}, "1 before": {"3": 9, "7": 4, "11": 10, "19": 6}, "nyk": {"21": 3}, "8 after": {"22": 4}}, "fga": {"all": {"0": 9, "1": 11, "2": 11, "3": 12, "4": 9, "5": 10, "6": 10, "7": 6, "8": 9, "9": 4, "10": 15, "11": 18, "12": 5, "13": 11, "14": 12, "15": 9, "16": 6, "17": 6, "18": 16, "19": 10, "20": 11, "21": 7, "22": 7}, "home": {"3": 12, "4": 9, "8": 9, "9": 4, "10": 15, "11": 18, "12": 5, "13": 11, "17": 6, "18": 16, "20": 11, "21": 7}, "away": {"0": 9, "1": 11, "2": 11, "5": 10, "6": 10, "7": 6, "14": 12, "15": 9, "16": 6, "19": 10, "22": 7}, "0 before": {"0": 9}, "3 after": {"0": 9, "11": 18, "21": 7}, "3 before": {"1": 11, "12": 5, "22": 7}, "2 after": {"1": 11, "3": 12, "4": 9, "5": 10, "7": 6, "8": 9, "9": 4, "12": 5, "13": 11, "14": 12, "15": 9, "16": 6, "17": 6, "19": 10, "20": 11}, "mon": {"1": 11, "5": 10, "9": 4, "16": 6, "20": 11}, "2 before": {"2": 11, "4": 9, "5": 10, "6": 10, "8": 9, "9": 4, "10": 15, "13": 11, "14": 12, "15": 9, "16": 6, "17": 6, "18": 16, "20": 11, "21": 7}, "1 after": {"2": 11, "6": 10, "10": 15, "18": 16}, "1 before": {"3": 12, "7": 6, "11": 18, "19": 10}, "nyk": {"21": 7}, "8 after": {"22": 7}}, "fg%": {"all": {"0": 33.3, "1": 63.6, "2": 54.5, "3": 75.0, "4": 88.9, "5": 50.0, "6": 30.0, "7": 66.7, "8": 66.7, "9": 75.0, "10": 66.7, "11": 55.6, "12": 60.0, "13": 54.5, "14": 58.3, "15": 44.4, "16": 33.3, "17": 50.0, "18": 56.3, "19": 60.0, "20": 36.4, "21": 42.9, "22": 57.1}, "home": {"3": 75.0, "4": 88.9, "8": 66.7, "9": 75.0, "10": 66.7, "11": 55.6, "12": 60.0, "13": 54.5, "17": 50.0, "18": 56.3, "20": 36.4, "21": 42.9}, "away": {"0": 33.3, "1": 63.6, "2": 54.5, "5": 50.0, "6": 30.0, "7": 66.7, "14": 58.3, "15": 44.4, "16": 33.3, "19": 60.0, "22": 57.1}, "0 before": {"0": 33.3}, "3 after": {"0": 33.3, "11": 55.6, "21": 42.9}, "3 before": {"1": 63.6, "12": 60.0, "22": 57.1}, "2 after": {"1": 63.6, "3": 75.0, "4": 88.9, "5": 50.0, "7": 66.7, "8": 66.7, "9": 75.0, "12": 60.0, "13": 54.5, "14": 58.3, "15": 44.4, "16": 33.3, "17": 50.0, "19": 60.0, "20": 36.4}, "mon": {"1": 63.6, "5": 50.0, "9": 75.0, "16": 33.3, "20": 36.4}, "2 before": {"2": 54.5, "4": 88.9, "5": 50.0, "6": 30.0, "8": 66.7, "9": 75.0, "10": 66.7, "13": 54.5, "14": 58.3, "15": 44.4, "16": 33.3, "17": 50.0, "18": 56.3, "20": 36.4, "21": 42.9}, "1 after": {"2": 54.5, "6": 30.0, "10": 66.7, "18": 56.3}, "1 before": {"3": 75.0, "7": 66.7, "11": 55.6, "19": 60.0}, "nyk": {"21": 42.9}, "8 after": {"22": 57.1}}, "3pm": {"all": {"0": 1, "1": 0, "2": 2, "3": 0, "4": 0, "5": 0, "6": 0, "7": 2, "8": 0, "9": 0, "10": 0, "11": 1, "12": 0, "13": 3, "14": 1, "15": 0, "16": 0, "17": 0, "18": 2, "19": 1, "20": 1, "21": 0, "22": 2}, "home": {"3": 0, "4": 0, "8": 0, "9": 0, "10": 0, "11": 1, "12": 0, "13": 3, "17": 0, "18": 2, "20": 1, "21": 0}, "away": {"0": 1, "1": 0, "2": 2, "5": 0, "6": 0, "7": 2, "14": 1, "15": 0, "16": 0, "19": 1, "22": 2}, "0 before": {"0": 1}, "3 after": {"0": 1, "11": 1, "21": 0}, "3 before": {"1": 0, "12": 0, "22": 2}, "2 after": {"1": 0, "3": 0, "4": 0, "5": 0, "7": 2, "8": 0, "9": 0, "12": 0, "13": 3, "14": 1, "15": 0, "16": 0, "17": 0, "19": 1, "20": 1}, "mon": {"1": 0, "5": 0, "9": 0, "16": 0, "20": 1}, "2 before": {"2": 2, "4": 0, "5": 0, "6": 0, "8": 0, "9": 0, "10": 0, "13": 3, "14": 1, "15": 0, "16": 0, "17": 0, "18": 2, "20": 1, "21": 0}, "1 after": {"2": 2, "6": 0, "10": 0, "18": 2}, "1 before": {"3": 0, "7": 2, "11": 1, "19": 1}, "nyk": {"21": 0}, "8 after": {"22": 2}}, "3pa": {"all": {"0": 4, "1": 0, "2": 4, "3": 1, "4": 1, "5": 1, "6": 2, "7": 2, "8": 0, "9": 0, "10": 1, "11": 3, "12": 2, "13": 5, "14": 1, "15": 2, "16": 1, "17": 0, "18": 3, "19": 1, "20": 5, "21": 1, "22": 4}, "home": {"3": 1, "4": 1, "8": 0, "9": 0, "10": 1, "11": 3, "12": 2, "13": 5, "17": 0, "18": 3, "20": 5, "21": 1}, "away": {"0": 4, "1": 0, "2": 4, "5": 1, "6": 2, "7": 2, "14": 1, "15": 2, "16": 1, "19": 1, "22": 4}, "0 before": {"0": 4}, "3 after": {"0": 4, "11": 3, "21": 1}, "3 before": {"1": 0, "12": 2, "22": 4}, "2 after": {"1": 0, "3": 1, "4": 1, "5": 1, "7": 2, "8": 0, "9": 0, "12": 2, "13": 5, "14": 1, "15": 2, "16": 1, "17": 0, "19": 1, "20": 5}, "mon": {"1": 0, "5": 1, "9": 0, "16": 1, "20": 5}, "2 before": {"2": 4, "4": 1, "5": 1, "6": 2, "8": 0, "9": 0, "10": 1, "13": 5, "14": 1, "15": 2, "16": 1, "17": 0, "18": 3, "20": 5, "21": 1}, "1 after": {"2": 4, "6": 2, "10": 1, "18": 3}, "1 before": {"3": 1, "7": 2, "11": 3, "19": 1}, "nyk": {"21": 1}, "8 after": {"22": 4}}, "3p%": {"all": {"0": 25.0, "1": 0.0, "2": 50.0, "3": 0.0, "4": 0.0, "5": 0.0, "6": 0.0, "7": 100.0, "8": 0.0, "9": 0.0, "10": 0.0, "11": 33.3, "12": 0.0, "13": 60.0, "14": 100.0, "15": 0.0, "16": 0.0, "17": 0.0, "18": 66.7, "19": 100.0, "20": 20.0, "21": 0.0, "22": 50.0}, "home": {"3": 0.0, "4": 0.0, "8": 0.0, "9": 0.0, "10": 0.0, "11": 33.3, "12": 0.0, "13": 60.0, "17": 0.0, "18": 66.7, "20": 20.0, "21": 0.0}, "away": {"0": 25.0, "1": 0.0, "2": 50.0, "5": 0.0, "6": 0.0, "7": 100.0, "14": 100.0, "15": 0.0, "16": 0.0, "19": 100.0, "22": 50.0}, "0 before": {"0": 25.0}, "3 after": {"0": 25.0, "11": 33.3, "21": 0.0}, "3 before": {"1": 0.0, "12": 0.0, "22": 50.0}, "2 after": {"1": 0.0, "3": 0.0, "4": 0.0, "5": 0.0, "7": 100.0, "8": 0.0, "9": 0.0, "12": 0.0, "13": 60.0, "14": 100.0, "15": 0.0, "16": 0.0, "17": 0.0, "19": 100.0, "20": 20.0}, "mon": {"1": 0.0, "5": 0.0, "9": 0.0, "16": 0.0, "20": 20.0}, "2 before": {"2": 50.0, "4": 0.0, "5": 0.0, "6": 0.0, "8": 0.0, "9": 0.0, "10": 0.0, "13": 60.0, "14": 100.0, "15": 0.0, "16": 0.0, "17": 0.0, "18": 66.7, "20": 20.0, "21": 0.0}, "1 after": {"2": 50.0, "6": 0.0, "10": 0.0, "18": 66.7}, "1 before": {"3": 0.0, "7": 100.0, "11": 33.3, "19": 100.0}, "nyk": {"21": 0.0}, "8 after": {"22": 50.0}}, "ftm": {"all": {"0": 2, "1": 4, "2": 1, "3": 6, "4": 3, "5": 4, "6": 2, "7": 2, "8": 3, "9": 4, "10": 6, "11": 1, "12": 0, "13": 0, "14": 0, "15": 0, "16": 2, "17": 0, "18": 3, "19": 6, "20": 2, "21": 2, "22": 2}, "home": {"3": 6, "4": 3, "8": 3, "9": 4, "10": 6, "11": 1, "12": 0, "13": 0, "17": 0, "18": 3, "20": 2, "21": 2}, "away": {"0": 2, "1": 4, "2": 1, "5": 4, "6": 2, "7": 2, "14": 0, "15": 0, "16": 2, "19": 6, "22": 2}, "0 before": {"0": 2}, "3 after": {"0": 2, "11": 1, "21": 2}, "3 before": {"1": 4, "12": 0, "22": 2}, "2 after": {"1": 4, "3": 6, "4": 3, "5": 4, "7": 2, "8": 3, "9": 4, "12": 0, "13": 0, "14": 0, "15": 0, "16": 2, "17": 0, "19": 6, "20": 2}, "mon": {"1": 4, "5": 4, "9": 4, "16": 2, "20": 2}, "2 before": {"2": 1, "4": 3, "5": 4, "6": 2, "8": 3, "9": 4, "10": 6, "13": 0, "14": 0, "15": 0, "16": 2, "17": 0, "18": 3, "20": 2, "21": 2}, "1 after": {"2": 1, "6": 2, "10": 6, "18": 3}, "1 before": {"3": 6, "7": 2, "11": 1, "19": 6}, "nyk": {"21": 2}, "8 after": {"22": 2}}, "fta": {"all": {"0": 2, "1": 4, "2": 2, "3": 7, "4": 3, "5": 6, "6": 4, "7": 2, "8": 4, "9": 4, "10": 6, "11": 3, "12": 0, "13": 0, "14": 1, "15": 0, "16": 2, "17": 0, "18": 4, "19": 7, "20": 2, "21": 2, "22": 2}, "home": {"3": 7, "4": 3, "8": 4, "9": 4, "10": 6, "11": 3, "12": 0, "13": 0, "17": 0, "18": 4, "20": 2, "21": 2}, "away": {"0": 2, "1": 4, "2": 2, "5": 6, "6": 4, "7": 2, "14": 1, "15": 0, "16": 2, "19": 7, "22": 2}, "0 before": {"0": 2}, "3 after": {"0": 2, "11": 3, "21": 2}, "3 before": {"1": 4, "12": 0, "22": 2}, "2 after": {"1": 4, "3": 7, "4": 3, "5": 6, "7": 2, "8": 4, "9": 4, "12": 0, "13": 0, "14": 1, "15": 0, "16": 2, "17": 0, "19": 7, "20": 2}, "mon": {"1": 4, "5": 6, "9": 4, "16": 2, "20": 2}, "2 before": {"2": 2, "4": 3, "5": 6, "6": 4, "8": 4, "9": 4, "10": 6, "13": 0, "14": 1, "15": 0, "16": 2, "17": 0, "18": 4, "20": 2, "21": 2}, "1 after": {"2": 2, "6": 4, "10": 6, "18": 4}, "1 before": {"3": 7, "7": 2, "11": 3, "19": 7}, "nyk": {"21": 2}, "8 after": {"22": 2}}, "ft%": {"all": {"0": 100.0, "1": 100.0, "2": 50.0, "3": 85.7, "4": 100.0, "5": 66.7, "6": 50.0, "7": 100.0, "8": 75.0, "9": 100.0, "10": 100.0, "11": 33.3, "12": 0.0, "13": 0.0, "14": 0.0, "15": 0.0, "16": 100.0, "17": 0.0, "18": 75.0, "19": 85.7, "20": 100.0, "21": 100.0, "22": 100.0}, "home": {"3": 85.7, "4": 100.0, "8": 75.0, "9": 100.0, "10": 100.0, "11": 33.3, "12": 0.0, "13": 0.0, "17": 0.0, "18": 75.0, "20": 100.0, "21": 100.0}, "away": {"0": 100.0, "1": 100.0, "2": 50.0, "5": 66.7, "6": 50.0, "7": 100.0, "14": 0.0, "15": 0.0, "16": 100.0, "19": 85.7, "22": 100.0}, "0 before": {"0": 100.0}, "3 after": {"0": 100.0, "11": 33.3, "21": 100.0}, "3 before": {"1": 100.0, "12": 0.0, "22": 100.0}, "2 after": {"1": 100.0, "3": 85.7, "4": 100.0, "5": 66.7, "7": 100.0, "8": 75.0, "9": 100.0, "12": 0.0, "13": 0.0, "14": 0.0, "15": 0.0, "16": 100.0, "17": 0.0, "19": 85.7, "20": 100.0}, "mon": {"1": 100.0, "5": 66.7, "9": 100.0, "16": 100.0, "20": 100.0}, "2 before": {"2": 50.0, "4": 100.0, "5": 66.7, "6": 50.0, "8": 75.0, "9": 100.0, "10": 100.0, "13": 0.0, "14": 0.0, "15": 0.0, "16": 100.0, "17": 0.0, "18": 75.0, "20": 100.0, "21": 100.0}, "1 after": {"2": 50.0, "6": 50.0, "10": 100.0, "18": 75.0}, "1 before": {"3": 85.7, "7": 100.0, "11": 33.3, "19": 85.7}, "nyk": {"21": 100.0}, "8 after": {"22": 100.0}}, "blk": {"all": {"0": 3, "1": 0, "2": 0, "3": 2, "4": 0, "5": 1, "6": 0, "7": 0, "8": 0, "9": 3, "10": 3, "11": 1, "12": 2, "13": 2, "14": 4, "15": 0, "16": 1, "17": 1, "18": 3, "19": 1, "20": 2, "21": 0, "22": 1}, "home": {"3": 2, "4": 0, "8": 0, "9": 3, "10": 3, "11": 1, "12": 2, "13": 2, "17": 1, "18": 3, "20": 2, "21": 0}, "away": {"0": 3, "1": 0, "2": 0, "5": 1, "6": 0, "7": 0, "14": 4, "15": 0, "16": 1, "19": 1, "22": 1}, "0 before": {"0": 3}, "3 after": {"0": 3, "11": 1, "21": 0}, "3 before": {"1": 0, "12": 2, "22": 1}, "2 after": {"1": 0, "3": 2, "4": 0, "5": 1, "7": 0, "8": 0, "9": 3, "12": 2, "13": 2, "14": 4, "15": 0, "16": 1, "17": 1, "19": 1, "20": 2}, "mon": {"1": 0, "5": 1, "9": 3, "16": 1, "20": 2}, "2 before": {"2": 0, "4": 0, "5": 1, "6": 0, "8": 0, "9": 3, "10": 3, "13": 2, "14": 4, "15": 0, "16": 1, "17": 1, "18": 3, "20": 2, "21": 0}, "1 after": {"2": 0, "6": 0, "10": 3, "18": 3}, "1 before": {"3": 2, "7": 0, "11": 1, "19": 1}, "nyk": {"21": 0}, "8 after": {"22": 1}}, "stl": {"all": {"0": 1, "1": 0, "2": 0, "3": 1, "4": 0, "5": 0, "6": 1, "7": 1, "8": 0, "9": 1, "10": 1, "11": 0, "12": 1, "13": 0, "14": 0, "15": 0, "16": 0, "17": 1, "18": 0, "19": 1, "20": 0, "21": 1, "22": 0}, "home": {"3": 1, "4": 0, "8": 0, "9": 1, "10": 1, "11": 0, "12": 1, "13": 0, "17": 1, "18": 0, "20": 0, "21": 1}, "away": {"0": 1, "1": 0, "2": 0, "5": 0, "6": 1, "7": 1, "14": 0, "15": 0, "16": 0, "19": 1, "22": 0}, "0 before": {"0": 1}, "3 after": {"0": 1, "11": 0, "21": 1}, "3 before": {"1": 0, "12": 1, "22": 0}, "2 after": {"1": 0, "3": 1, "4": 0, "5": 0, "7": 1, "8": 0, "9": 1, "12": 1, "13": 0, "14": 0, "15": 0, "16": 0, "17": 1, "19": 1, "20": 0}, "mon": {"1": 0, "5": 0, "9": 1, "16": 0, "20": 0}, "2 before": {"2": 0, "4": 0, "5": 0, "6": 1, "8": 0, "9": 1, "10": 1, "13": 0, "14": 0, "15": 0, "16": 0, "17": 1, "18": 0, "20": 0, "21": 1}, "1 after": {"2": 0, "6": 1, "10": 1, "18": 0}, "1 before": {"3": 1, "7": 1, "11": 0, "19": 1}, "nyk": {"21": 1}, "8 after": {"22": 0}}, "pf": {"all": {"0": 2, "1": 6, "2": 3, "3": 3, "4": 5, "5": 3, "6": 2, "7": 4, "8": 5, "9": 3, "10": 5, "11": 4, "12": 1, "13": 0, "14": 6, "15": 1, "16": 6, "17": 1, "18": 5, "19": 2, "20": 1, "21": 4, "22": 1}, "home": {"3": 3, "4": 5, "8": 5, "9": 3, "10": 5, "11": 4, "12": 1, "13": 0, "17": 1, "18": 5, "20": 1, "21": 4}, "away": {"0": 2, "1": 6, "2": 3, "5": 3, "6": 2, "7": 4, "14": 6, "15": 1, "16": 6, "19": 2, "22": 1}, "0 before": {"0": 2}, "3 after": {"0": 2, "11": 4, "21": 4}, "3 before": {"1": 6, "12": 1, "22": 1}, "2 after": {"1": 6, "3": 3, "4": 5, "5": 3, "7": 4, "8": 5, "9": 3, "12": 1, "13": 0, "14": 6, "15": 1, "16": 6, "17": 1, "19": 2, "20": 1}, "mon": {"1": 6, "5": 3, "9": 3, "16": 6, "20": 1}, "2 before": {"2": 3, "4": 5, "5": 3, "6": 2, "8": 5, "9": 3, "10": 5, "13": 0, "14": 6, "15": 1, "16": 6, "17": 1, "18": 5, "20": 1, "21": 4}, "1 after": {"2": 3, "6": 2, "10": 5, "18": 5}, "1 before": {"3": 3, "7": 4, "11": 4, "19": 2}, "nyk": {"21": 4}, "8 after": {"22": 1}}, "to": {"all": {"0": 1, "1": 1, "2": 0, "3": 1, "4": 2, "5": 0, "6": 1, "7": 1, "8": 1, "9": 0, "10": 3, "11": 0, "12": 0, "13": 0, "14": 2, "15": 0, "16": 2, "17": 3, "18": 2, "19": 0, "20": 0, "21": 4, "22": 3}, "home": {"3": 1, "4": 2, "8": 1, "9": 0, "10": 3, "11": 0, "12": 0, "13": 0, "17": 3, "18": 2, "20": 0, "21": 4}, "away": {"0": 1, "1": 1, "2": 0, "5": 0, "6": 1, "7": 1, "14": 2, "15": 0, "16": 2, "19": 0, "22": 3}, "0 before": {"0": 1}, "3 after": {"0": 1, "11": 0, "21": 4}, "3 before": {"1": 1, "12": 0, "22": 3}, "2 after": {"1": 1, "3": 1, "4": 2, "5": 0, "7": 1, "8": 1, "9": 0, "12": 0, "13": 0, "14": 2, "15": 0, "16": 2, "17": 3, "19": 0, "20": 0}, "mon": {"1": 1, "5": 0, "9": 0, "16": 2, "20": 0}, "2 before": {"2": 0, "4": 2, "5": 0, "6": 1, "8": 1, "9": 0, "10": 3, "13": 0, "14": 2, "15": 0, "16": 2, "17": 3, "18": 2, "20": 0, "21": 4}, "1 after": {"2": 0, "6": 1, "10": 3, "18": 2}, "1 before": {"3": 1, "7": 1, "11": 0, "19": 0}, "nyk": {"21": 4}, "8 after": {"22": 3}}}}